tky2jgd.py
tky2jgd-0.1.0.dist-info/LICENSE
tky2jgd-0.1.0.dist-info/WHEEL
tky2jgd-0.1.0.dist-info/METADATA
tky2jgd-0.1.0.dist-info/RECORD
