Metadata-Version: 2.1
Name: tky2jgd
Version: 0.1.0
Summary: Python port of TKY2JGD to transform coordinates from Tokyo Datum (EPSG:4301) to JGD2000 (EPSG:4612)
Home-page: https://github.com/shuuji3/TKY2JGD
License: BSD-3-Clause
Author: TAKAHASHI Shuuji
Author-email: shuuji3@gmail.com
Maintainer: TAKAHASHI Shuuji
Maintainer-email: shuuji3@gmail.com
Requires-Python: >=3.9,<4.0
Classifier: License :: OSI Approved :: BSD License
Classifier: Programming Language :: Python :: 3
Classifier: Programming Language :: Python :: 3.9
Project-URL: Repository, https://github.com/shuuji3/TKY2JGD
